luisa/atomic.py
luisa/util.py
luisa/raster.py
luisa/mathtypes.pyi
luisa/hit.py
luisa/struct.py
luisa/builtin.py
luisa/array.py
luisa/globalvars.py
luisa/meshformat.py
luisa/types.py
luisa/reftest.py
luisa/rayquery.py
luisa/bindless.py
luisa/image2d.py
luisa/mathtypes.py
luisa/__init__.py
luisa/buffer.py
luisa/framerate.py
luisa/astbuilder.py
luisa/accel.py
luisa/gui.py
luisa/callable_lib.py
luisa/vector.py
luisa/autodiff.py
luisa/raster_func.py
luisa/image3d.py
luisa/func.py
luisa/lcapi.pyi
luisa/dylibs/liblc-ext-eastl.so
luisa/dylibs/liblc-backend-cuda.so
luisa/dylibs/luisa_nvrtc
luisa/dylibs/liblc-dsl.so
luisa/dylibs/liblc-runtime.so
luisa/dylibs/libluisa_compute_api_types.a
luisa/dylibs/liblc-ext-glfw.so.3.5
luisa/dylibs/liblc-ext-glfw.so.3
luisa/dylibs/liblc-ext-glfw.so
luisa/dylibs/liblc-ir-v2.so
luisa/dylibs/lcapi.cpython-310-x86_64-linux-gnu.so
luisa/dylibs/liblc-api.so
luisa/dylibs/liblc-backend-cpu.so
luisa/dylibs/liblc-gui.so
luisa/dylibs/libluisa_compute_backend_impl.so
luisa/dylibs/liblc-ext-imgui.so
luisa/dylibs/liblc-vstl.so
luisa/dylibs/libembree4.so.4
luisa/dylibs/liblc-validation-layer.so
luisa/dylibs/liblc-tensor.so
luisa/dylibs/liblc-ast.so
luisa/dylibs/liblc-osl.so
luisa/dylibs/libembree4.so
luisa/dylibs/liblc-ir.so
luisa/dylibs/libcudadevrt.a
luisa/dylibs/libluisa_compute_ir_static.a
luisa/dylibs/liblc-backend-remote.so
luisa/dylibs/liblc-core.so
luisa/dylibs/liblc-ext-stb.so
luisa_python-0.3.7.dist-info/METADATA
luisa_python-0.3.7.dist-info/WHEEL
luisa_python-0.3.7.dist-info/entry_points.txt
luisa_python-0.3.7.dist-info/RECORD
luisa_python-0.3.7.dist-info/licenses/LICENSE
luisa_python.libs/libuuid-48d6f845.so.1.3.0
