Metadata-Version: 2.1
Name: luisa-python
Version: 0.3.7
Summary: A High-Performance Rendering Framework with Layered and Unified Interfaces on Stream Architectures
Author: LuisaGroup
License: BSD 3-Clause License
Classifier: Development Status :: 4 - Beta
Classifier: License :: OSI Approved :: BSD License
Classifier: Programming Language :: Python :: 3 :: Only
Classifier: Programming Language :: Python :: 3.10
Classifier: Programming Language :: Python :: 3.11
Classifier: Programming Language :: Python :: 3.12
Requires-Python: >=3.10
Requires-Dist: sourceinspect
Requires-Dist: numpy
License-File: LICENSE
